felafax/__init__.py
felafax/trainer_engine/__init__.py
felafax/trainer_engine/checkpoint.py
felafax/trainer_engine/data/__init__.py
felafax/trainer_engine/data/data.py
felafax/trainer_engine/models/__init__.py
felafax/trainer_engine/models/llama3/__init__.py
felafax/trainer_engine/models/llama3/jax/__init__.py
felafax/trainer_engine/models/llama3/jax/model.py
felafax/trainer_engine/setup.py
felafax/trainer_engine/trainer.py
felafax/trainer_engine/utils.py
felafax-1.0.12.dist-info/LICENSE
felafax-1.0.12.dist-info/METADATA
felafax-1.0.12.dist-info/WHEEL
felafax-1.0.12.dist-info/RECORD
