Metadata-Version: 2.1
Name: felafax
Version: 1.0.12
Summary: felafax
Home-page: https://github.com/felafax/felafax
License: Apache-2.0
Author: Nithin
Author-email: nithin@felafax.ai
Requires-Python: >=3.10,<4.0
Classifier: License :: OSI Approved :: Apache Software License
Classifier: Programming Language :: Python :: 3
Classifier: Programming Language :: Python :: 3.10
Classifier: Programming Language :: Python :: 3.11
Classifier: Programming Language :: Python :: 3.12
Requires-Dist: absl-py (>=2.1.0,<3.0.0)
Requires-Dist: accelerate (>=0.26.0)
Requires-Dist: aiofiles (>=24.1.0,<25.0.0)
Requires-Dist: cloudpickle (>=3.1.0,<4.0.0)
Requires-Dist: datasets (>=2.18.0)
Requires-Dist: einops (>=0.8.0,<0.9.0)
Requires-Dist: equinox (>=0.11.8)
Requires-Dist: flax[all]
Requires-Dist: fsspec (<2024.10.0)
Requires-Dist: gcsfs (<2024.10.0)
Requires-Dist: huggingface-hub (>=0.26.2,<0.27.0)
Requires-Dist: jax (>=0.4.35,<0.5.0)
Requires-Dist: jaxlib (>=0.4.35,<0.5.0)
Requires-Dist: jaxtyping (==0.2.25)
Requires-Dist: matplotlib (>=3.9.2,<4.0.0)
Requires-Dist: memory-profiler (>=0.61.0,<0.62.0)
Requires-Dist: ml-collections (>=1.0.0,<2.0.0)
Requires-Dist: ml-dtypes (>=0.5.0,<0.6.0)
Requires-Dist: numpy (>=2.1.3,<3.0.0)
Requires-Dist: optax (>=0.2.4,<0.3.0)
Requires-Dist: orbax (>=0.1.9,<0.2.0)
Requires-Dist: pyrallis (>=0.3.1,<0.4.0)
Requires-Dist: pytest (>=8.3.3,<9.0.0)
Requires-Dist: python-dotenv (>=1.0.1,<2.0.0)
Requires-Dist: quax (>=0.0.5,<0.0.6)
Requires-Dist: requests
Requires-Dist: ruff (==0.2.2)
Requires-Dist: sentencepiece (>=0.2.0,<0.3.0)
Requires-Dist: tqdm (>=4.67.0,<5.0.0)
Requires-Dist: transformers (>=4.43)
Requires-Dist: typeguard (==2.13.3)
Requires-Dist: typing-extensions (>=4.12.2,<5.0.0)
Requires-Dist: urllib3 (>=2.2.3,<3.0.0)
Project-URL: Bug Tracker, https://github.com/felafax/felafax/issues
Project-URL: Documentation, https://github.com/felafax/felafax
Project-URL: Repository, https://github.com/felafax/felafax
